azure/__init__.py
azure/cli/__init__.py
azure/cli/command_modules/__init__.py
azure/cli/command_modules/acr/__init__.py
azure/cli/command_modules/acr/_archive_utils.py
azure/cli/command_modules/acr/_azure_utils.py
azure/cli/command_modules/acr/_client_factory.py
azure/cli/command_modules/acr/_constants.py
azure/cli/command_modules/acr/_docker_utils.py
azure/cli/command_modules/acr/_errors.py
azure/cli/command_modules/acr/_format.py
azure/cli/command_modules/acr/_help.py
azure/cli/command_modules/acr/_params.py
azure/cli/command_modules/acr/_run_polling.py
azure/cli/command_modules/acr/_stream_utils.py
azure/cli/command_modules/acr/_utils.py
azure/cli/command_modules/acr/_validators.py
azure/cli/command_modules/acr/build.py
azure/cli/command_modules/acr/check_health.py
azure/cli/command_modules/acr/commands.py
azure/cli/command_modules/acr/credential.py
azure/cli/command_modules/acr/custom.py
azure/cli/command_modules/acr/helm.py
azure/cli/command_modules/acr/import.py
azure/cli/command_modules/acr/network_rule.py
azure/cli/command_modules/acr/pack.py
azure/cli/command_modules/acr/policy.py
azure/cli/command_modules/acr/replication.py
azure/cli/command_modules/acr/repository.py
azure/cli/command_modules/acr/run.py
azure/cli/command_modules/acr/task.py
azure/cli/command_modules/acr/template.json
azure/cli/command_modules/acr/template_existing_storage.json
azure/cli/command_modules/acr/template_new_storage.json
azure/cli/command_modules/acr/webhook.py
opal_azure_cli_acr-2.2.12.dist-info/METADATA
opal_azure_cli_acr-2.2.12.dist-info/WHEEL
opal_azure_cli_acr-2.2.12.dist-info/top_level.txt
opal_azure_cli_acr-2.2.12.dist-info/RECORD
