Metadata-Version: 2.1
Name: opal-azure-cli-acr
Version: 2.2.12
Summary: Microsoft Azure Command-Line Tools ACR Command Module
Home-page: https://github.com/Azure/azure-cli
Author: Microsoft Corporation
Author-email: azpycli@microsoft.com
License: MIT
Platform: UNKNOWN
Classifier: Development Status :: 4 - Beta
Classifier: Intended Audience :: Developers
Classifier: Intended Audience :: System Administrators
Classifier: Programming Language :: Python
Classifier: Programming Language :: Python :: 2
Classifier: Programming Language :: Python :: 2.7
Classifier: Programming Language :: Python :: 3
Classifier: Programming Language :: Python :: 3.4
Classifier: Programming Language :: Python :: 3.5
Classifier: Programming Language :: Python :: 3.6
Classifier: License :: OSI Approved :: MIT License
Requires-Dist: opal-azure-cli-core (>=2.0.68)
Requires-Dist: azure-mgmt-storage (==3.3.0)
Requires-Dist: azure-storage-blob (==1.3.1)
Requires-Dist: azure-mgmt-containerregistry (==2.8.0)
Requires-Dist: azure-cli-command-modules-nspkg (>=2.0.0)
